[
    {
        "id": 150365926,
        "tournament_id": 9980037,
        "name": "Gatorx",
        "seed": 1,
        "active": true,
        "created_at": "2021/07/09",
        "updated_at": "2021/07/09",
        "invite_email": null,
        "final_rank": 3,
        "misc": null,
        "icon": null,
        "on_waiting_list": false,
        "invitation_id": null,
        "group_id": null,
        "checked_in_at": "2021/07/09",
        "ranked_member_id": null,
        "custom_field_response": {
            "16432": "Yes",
            "16433": "Yes",
            "16434": "true"
        },
        "clinch": null,
        "integration_uids": null,
        "challonge_username": "Gatorx",
        "challonge_user_id": 3307777,
        "challonge_email_address_verified": true,
        "removable": false,
        "participatable_or_invitation_attached": true,
        "confirm_remove": true,
        "invitation_pending": false,
        "display_name_with_invitation_email_address": "Gatorx",
        "email_hash": "c54a9bd077f47926e129280a30bd50bc",
        "username": "Gatorx",
        "display_name": "Gatorx",
        "attached_participatable_portrait_url": "https://secure.gravatar.com/avatar/c54a9bd077f47926e129280a30bd50bc?r=r&s=96&d=https://s3.amazonaws.com/challonge_app/misc/challonge_fireball_gray.png",
        "can_check_in": false,
        "checked_in": true,
        "reactivatable": false,
        "check_in_open": false,
        "group_player_ids": [],
        "has_irrelevant_seed": false,
        "ordinal_seed": "1st",
        "roster_complete": null,
        "roster_size": null
    },
    {
        "id": 150354532,
        "tournament_id": 9980037,
        "name": "KageMaru11",
        "seed": 2,
        "active": true,
        "created_at": "2021/07/09",
        "updated_at": "2021/07/09",
        "invite_email": null,
        "final_rank": 5,
        "misc": null,
        "icon": null,
        "on_waiting_list": false,
        "invitation_id": null,
        "group_id": null,
        "checked_in_at": "2021/07/09",
        "ranked_member_id": null,
        "custom_field_response": {
            "16432": "Yes",
            "16433": "No, but I'll do it now!",
            "16434": "true"
        },
        "clinch": null,
        "integration_uids": null,
        "challonge_username": "KageMaru11",
        "challonge_user_id": 3151367,
        "challonge_email_address_verified": true,
        "removable": false,
        "participatable_or_invitation_attached": true,
        "confirm_remove": true,
        "invitation_pending": false,
        "display_name_with_invitation_email_address": "KageMaru11",
        "email_hash": "5fdee70ed24f1e1ef8b7d0bebcfa5cf2",
        "username": "KageMaru11",
        "display_name": "KageMaru11",
        "attached_participatable_portrait_url": "https://secure.gravatar.com/avatar/5fdee70ed24f1e1ef8b7d0bebcfa5cf2?r=r&s=96&d=https://s3.amazonaws.com/challonge_app/misc/challonge_fireball_gray.png",
        "can_check_in": false,
        "checked_in": true,
        "reactivatable": false,
        "check_in_open": false,
        "group_player_ids": [],
        "has_irrelevant_seed": false,
        "ordinal_seed": "2nd",
        "roster_complete": null,
        "roster_size": null
    },
    {
        "id": 150368170,
        "tournament_id": 9980037,
        "name": "Baillie",
        "seed": 3,
        "active": true,
        "created_at": "2021/07/09",
        "updated_at": "2021/07/09",
        "invite_email": null,
        "final_rank": 9,
        "misc": null,
        "icon": null,
        "on_waiting_list": false,
        "invitation_id": null,
        "group_id": null,
        "checked_in_at": "2021/07/09",
        "ranked_member_id": null,
        "custom_field_response": {
            "16432": "Yes",
            "16433": "Yes"
        },
        "clinch": null,
        "integration_uids": null,
        "challonge_username": "Baillie",
        "challonge_user_id": 4368499,
        "challonge_email_address_verified": true,
        "removable": false,
        "participatable_or_invitation_attached": true,
        "confirm_remove": true,
        "invitation_pending": false,
        "display_name_with_invitation_email_address": "Baillie",
        "email_hash": "644d6aaa445a6483116b865f447c65a6",
        "username": "Baillie",
        "display_name": "Baillie",
        "attached_participatable_portrait_url": "https://s3.amazonaws.com/challonge_app/users/images/004/368/499/xlarge/bat.png",
        "can_check_in": false,
        "checked_in": true,
        "reactivatable": false,
        "check_in_open": false,
        "group_player_ids": [],
        "has_irrelevant_seed": false,
        "ordinal_seed": "3rd",
        "roster_complete": null,
        "roster_size": null
    },
    {
        "id": 150367820,
        "tournament_id": 9980037,
        "name": "Kyboi",
        "seed": 4,
        "active": true,
        "created_at": "2021/07/09",
        "updated_at": "2021/07/09",
        "invite_email": null,
        "final_rank": 9,
        "misc": null,
        "icon": null,
        "on_waiting_list": false,
        "invitation_id": null,
        "group_id": null,
        "checked_in_at": "2021/07/09",
        "ranked_member_id": null,
        "custom_field_response": {
            "16432": "Yes",
            "16433": "No, but I'll do it now!",
            "16434": "true"
        },
        "clinch": null,
        "integration_uids": null,
        "challonge_username": "KyboiGG",
        "challonge_user_id": 2461647,
        "challonge_email_address_verified": true,
        "removable": false,
        "participatable_or_invitation_attached": true,
        "confirm_remove": true,
        "invitation_pending": false,
        "display_name_with_invitation_email_address": "Kyboi",
        "email_hash": "605054216b02dca1cd1681d3f2edb4ef",
        "username": "KyboiGG",
        "display_name": "Kyboi",
        "attached_participatable_portrait_url": "https://secure.gravatar.com/avatar/605054216b02dca1cd1681d3f2edb4ef?r=r&s=96&d=https://s3.amazonaws.com/challonge_app/misc/challonge_fireball_gray.png",
        "can_check_in": false,
        "checked_in": true,
        "reactivatable": false,
        "check_in_open": false,
        "group_player_ids": [],
        "has_irrelevant_seed": false,
        "ordinal_seed": "4th",
        "roster_complete": null,
        "roster_size": null
    },
    {
        "id": 149625762,
        "tournament_id": 9980037,
        "name": "PhleBuster",
        "seed": 5,
        "active": true,
        "created_at": "2021/06/29",
        "updated_at": "2021/06/29",
        "invite_email": null,
        "final_rank": 5,
        "misc": null,
        "icon": null,
        "on_waiting_list": false,
        "invitation_id": null,
        "group_id": null,
        "checked_in_at": "2021/07/09",
        "ranked_member_id": null,
        "custom_field_response": {
            "16432": "Yes",
            "16433": "No, but I'll do it now!",
            "16434": "true"
        },
        "clinch": null,
        "integration_uids": null,
        "challonge_username": "PhleBuster",
        "challonge_user_id": 2736070,
        "challonge_email_address_verified": true,
        "removable": false,
        "participatable_or_invitation_attached": true,
        "confirm_remove": true,
        "invitation_pending": false,
        "display_name_with_invitation_email_address": "PhleBuster",
        "email_hash": "126720b4fd70100fd14530fc179f252f",
        "username": "PhleBuster",
        "display_name": "PhleBuster",
        "attached_participatable_portrait_url": "https://s3.amazonaws.com/challonge_app/users/images/002/736/070/xlarge/heshikoavatar4.png",
        "can_check_in": false,
        "checked_in": true,
        "reactivatable": false,
        "check_in_open": false,
        "group_player_ids": [],
        "has_irrelevant_seed": false,
        "ordinal_seed": "5th",
        "roster_complete": null,
        "roster_size": null
    },
    {
        "id": 149614515,
        "tournament_id": 9980037,
        "name": "papapanda",
        "seed": 6,
        "active": true,
        "created_at": "2021/06/28",
        "updated_at": "2021/06/28",
        "invite_email": null,
        "final_rank": 5,
        "misc": null,
        "icon": null,
        "on_waiting_list": false,
        "invitation_id": null,
        "group_id": null,
        "checked_in_at": "2021/07/09",
        "ranked_member_id": null,
        "custom_field_response": {
            "16432": "Yes",
            "16433": "Yes",
            "16434": "true"
        },
        "clinch": null,
        "integration_uids": null,
        "challonge_username": "papapanda",
        "challonge_user_id": 135102,
        "challonge_email_address_verified": true,
        "removable": false,
        "participatable_or_invitation_attached": true,
        "confirm_remove": true,
        "invitation_pending": false,
        "display_name_with_invitation_email_address": "papapanda",
        "email_hash": "053d13ecc96168ae827232b73abb5ac6",
        "username": "papapanda",
        "display_name": "papapanda",
        "attached_participatable_portrait_url": "https://s3.amazonaws.com/challonge_app/users/images/000/135/102/xlarge/Sasaki.Saku.full.2508930.png",
        "can_check_in": false,
        "checked_in": true,
        "reactivatable": false,
        "check_in_open": false,
        "group_player_ids": [],
        "has_irrelevant_seed": false,
        "ordinal_seed": "6th",
        "roster_complete": null,
        "roster_size": null
    },
    {
        "id": 150345262,
        "tournament_id": 9980037,
        "name": "MrLEz",
        "seed": 7,
        "active": true,
        "created_at": "2021/07/09",
        "updated_at": "2021/07/09",
        "invite_email": null,
        "final_rank": 3,
        "misc": null,
        "icon": null,
        "on_waiting_list": false,
        "invitation_id": null,
        "group_id": null,
        "checked_in_at": "2021/07/09",
        "ranked_member_id": null,
        "custom_field_response": {
            "16432": "Yes",
            "16433": "Yes"
        },
        "clinch": null,
        "integration_uids": null,
        "challonge_username": "MrLEz",
        "challonge_user_id": 4206724,
        "challonge_email_address_verified": true,
        "removable": false,
        "participatable_or_invitation_attached": true,
        "confirm_remove": true,
        "invitation_pending": false,
        "display_name_with_invitation_email_address": "MrLEz",
        "email_hash": "86af98c01e0a9db5531e9274386f7cf9",
        "username": "MrLEz",
        "display_name": "MrLEz",
        "attached_participatable_portrait_url": "https://s3.amazonaws.com/challonge_app/users/images/004/206/724/xlarge/1241231.png",
        "can_check_in": false,
        "checked_in": true,
        "reactivatable": false,
        "check_in_open": false,
        "group_player_ids": [],
        "has_irrelevant_seed": false,
        "ordinal_seed": "7th",
        "roster_complete": null,
        "roster_size": null
    },
    {
        "id": 150365191,
        "tournament_id": 9980037,
        "name": "XenoDactyl",
        "seed": 8,
        "active": true,
        "created_at": "2021/07/09",
        "updated_at": "2021/07/09",
        "invite_email": null,
        "final_rank": 5,
        "misc": null,
        "icon": null,
        "on_waiting_list": false,
        "invitation_id": null,
        "group_id": null,
        "checked_in_at": "2021/07/09",
        "ranked_member_id": null,
        "custom_field_response": {
            "16432": "Yes",
            "16433": "Yes",
            "16434": "true"
        },
        "clinch": null,
        "integration_uids": null,
        "challonge_username": "XenoDactyl",
        "challonge_user_id": 959616,
        "challonge_email_address_verified": true,
        "removable": false,
        "participatable_or_invitation_attached": true,
        "confirm_remove": true,
        "invitation_pending": false,
        "display_name_with_invitation_email_address": "XenoDactyl",
        "email_hash": "979450d822cd151d27d7006de0ecf7fa",
        "username": "XenoDactyl",
        "display_name": "XenoDactyl",
        "attached_participatable_portrait_url": "https://s3.amazonaws.com/challonge_app/users/images/000/959/616/xlarge/IMG_2151.png",
        "can_check_in": false,
        "checked_in": true,
        "reactivatable": false,
        "check_in_open": false,
        "group_player_ids": [],
        "has_irrelevant_seed": false,
        "ordinal_seed": "8th",
        "roster_complete": null,
        "roster_size": null
    },
    {
        "id": 150365620,
        "tournament_id": 9980037,
        "name": "SC2BeNeFiT",
        "seed": 9,
        "active": true,
        "created_at": "2021/07/09",
        "updated_at": "2021/07/09",
        "invite_email": null,
        "final_rank": 9,
        "misc": null,
        "icon": null,
        "on_waiting_list": false,
        "invitation_id": null,
        "group_id": null,
        "checked_in_at": "2021/07/09",
        "ranked_member_id": null,
        "custom_field_response": {
            "16432": "Yes",
            "16433": "No, but I'll do it now!",
            "16434": "true"
        },
        "clinch": null,
        "integration_uids": null,
        "challonge_username": "SC2BeNeFiT",
        "challonge_user_id": 4343873,
        "challonge_email_address_verified": true,
        "removable": false,
        "participatable_or_invitation_attached": true,
        "confirm_remove": true,
        "invitation_pending": false,
        "display_name_with_invitation_email_address": "SC2BeNeFiT",
        "email_hash": "ec13a5a788ea36337bfbc2606e8b03fc",
        "username": "SC2BeNeFiT",
        "display_name": "SC2BeNeFiT",
        "attached_participatable_portrait_url": "https://s3.amazonaws.com/challonge_app/users/images/004/343/873/xlarge/Screen_Shot_2022-03-13_at_2.49.30_PM.png",
        "can_check_in": false,
        "checked_in": true,
        "reactivatable": false,
        "check_in_open": false,
        "group_player_ids": [],
        "has_irrelevant_seed": false,
        "ordinal_seed": "9th",
        "roster_complete": null,
        "roster_size": null
    },
    {
        "id": 149924052,
        "tournament_id": 9980037,
        "name": "Maya_SC2",
        "seed": 10,
        "active": true,
        "created_at": "2021/07/03",
        "updated_at": "2021/07/03",
        "invite_email": null,
        "final_rank": 9,
        "misc": null,
        "icon": null,
        "on_waiting_list": false,
        "invitation_id": null,
        "group_id": null,
        "checked_in_at": "2021/07/09",
        "ranked_member_id": null,
        "custom_field_response": {
            "16432": "Yes",
            "16433": "No, but I'll do it now!"
        },
        "clinch": null,
        "integration_uids": null,
        "challonge_username": "grapefruitman",
        "challonge_user_id": 4740777,
        "challonge_email_address_verified": true,
        "removable": false,
        "participatable_or_invitation_attached": true,
        "confirm_remove": true,
        "invitation_pending": false,
        "display_name_with_invitation_email_address": "Maya_SC2",
        "email_hash": "9f6f7c50caa4e8f09286aafab8deba33",
        "username": "grapefruitman",
        "display_name": "Maya_SC2",
        "attached_participatable_portrait_url": "https://secure.gravatar.com/avatar/9f6f7c50caa4e8f09286aafab8deba33?r=r&s=96&d=https://s3.amazonaws.com/challonge_app/misc/challonge_fireball_gray.png",
        "can_check_in": false,
        "checked_in": true,
        "reactivatable": false,
        "check_in_open": false,
        "group_player_ids": [],
        "has_irrelevant_seed": false,
        "ordinal_seed": "10th",
        "roster_complete": null,
        "roster_size": null
    },
    {
        "id": 150368638,
        "tournament_id": 9980037,
        "name": "AlpX_WarbuffII",
        "seed": 11,
        "active": true,
        "created_at": "2021/07/09",
        "updated_at": "2021/07/09",
        "invite_email": null,
        "final_rank": 9,
        "misc": null,
        "icon": null,
        "on_waiting_list": false,
        "invitation_id": null,
        "group_id": null,
        "checked_in_at": "2021/07/09",
        "ranked_member_id": null,
        "custom_field_response": {
            "16432": "Yes",
            "16433": "No, but I'll do it now!",
            "16434": "true"
        },
        "clinch": null,
        "integration_uids": null,
        "challonge_username": "AlpX_WarbuffII",
        "challonge_user_id": 1543355,
        "challonge_email_address_verified": true,
        "removable": false,
        "participatable_or_invitation_attached": true,
        "confirm_remove": true,
        "invitation_pending": false,
        "display_name_with_invitation_email_address": "AlpX_WarbuffII",
        "email_hash": "f86a60ecdca7f2ad5fbfe0123f2ac6d5",
        "username": "AlpX_WarbuffII",
        "display_name": "AlpX_WarbuffII",
        "attached_participatable_portrait_url": "https://s3.amazonaws.com/challonge_app/users/images/001/543/355/xlarge/Base_Buffalo.png",
        "can_check_in": false,
        "checked_in": true,
        "reactivatable": false,
        "check_in_open": false,
        "group_player_ids": [],
        "has_irrelevant_seed": false,
        "ordinal_seed": "11th",
        "roster_complete": null,
        "roster_size": null
    },
    {
        "id": 149631785,
        "tournament_id": 9980037,
        "name": "Cognite",
        "seed": 12,
        "active": true,
        "created_at": "2021/06/29",
        "updated_at": "2021/06/29",
        "invite_email": null,
        "final_rank": 9,
        "misc": null,
        "icon": null,
        "on_waiting_list": false,
        "invitation_id": null,
        "group_id": null,
        "checked_in_at": "2021/07/09",
        "ranked_member_id": null,
        "custom_field_response": {
            "16432": "Yes",
            "16433": "No, but I'll do it now!"
        },
        "clinch": null,
        "integration_uids": null,
        "challonge_username": "C0gnite",
        "challonge_user_id": 4093378,
        "challonge_email_address_verified": true,
        "removable": false,
        "participatable_or_invitation_attached": true,
        "confirm_remove": true,
        "invitation_pending": false,
        "display_name_with_invitation_email_address": "Cognite",
        "email_hash": "3410d670f74ba80cf4c0b04bc12d4ac6",
        "username": "C0gnite",
        "display_name": "Cognite",
        "attached_participatable_portrait_url": "https://s3.amazonaws.com/challonge_app/users/images/004/093/378/xlarge/tech_eye.png",
        "can_check_in": false,
        "checked_in": true,
        "reactivatable": false,
        "check_in_open": false,
        "group_player_ids": [],
        "has_irrelevant_seed": false,
        "ordinal_seed": "12th",
        "roster_complete": null,
        "roster_size": null
    },
    {
        "id": 149630306,
        "tournament_id": 9980037,
        "name": "AreZzzzz",
        "seed": 13,
        "active": true,
        "created_at": "2021/06/29",
        "updated_at": "2021/06/29",
        "invite_email": null,
        "final_rank": 1,
        "misc": null,
        "icon": null,
        "on_waiting_list": false,
        "invitation_id": null,
        "group_id": null,
        "checked_in_at": "2021/07/09",
        "ranked_member_id": null,
        "custom_field_response": {
            "16432": "Yes",
            "16433": "Yes",
            "16434": "true"
        },
        "clinch": null,
        "integration_uids": null,
        "challonge_username": "AreZzzzz",
        "challonge_user_id": 2307118,
        "challonge_email_address_verified": true,
        "removable": false,
        "participatable_or_invitation_attached": true,
        "confirm_remove": true,
        "invitation_pending": false,
        "display_name_with_invitation_email_address": "AreZzzzz",
        "email_hash": "78cb2fa750aaeac354d1a7d1888be2b6",
        "username": "AreZzzzz",
        "display_name": "AreZzzzz",
        "attached_participatable_portrait_url": "https://s3.amazonaws.com/challonge_app/users/images/002/307/118/xlarge/AreZ-Project.png",
        "can_check_in": false,
        "checked_in": true,
        "reactivatable": false,
        "check_in_open": false,
        "group_player_ids": [],
        "has_irrelevant_seed": false,
        "ordinal_seed": "13th",
        "roster_complete": null,
        "roster_size": null
    },
    {
        "id": 150367930,
        "tournament_id": 9980037,
        "name": "CharactR",
        "seed": 14,
        "active": true,
        "created_at": "2021/07/09",
        "updated_at": "2021/07/09",
        "invite_email": null,
        "final_rank": 17,
        "misc": null,
        "icon": null,
        "on_waiting_list": false,
        "invitation_id": null,
        "group_id": null,
        "checked_in_at": "2021/07/09",
        "ranked_member_id": null,
        "custom_field_response": {
            "16432": "Yes",
            "16433": "No, but I'll do it now!",
            "16434": "true"
        },
        "clinch": null,
        "integration_uids": null,
        "challonge_username": "CharactR",
        "challonge_user_id": 3124063,
        "challonge_email_address_verified": true,
        "removable": false,
        "participatable_or_invitation_attached": true,
        "confirm_remove": true,
        "invitation_pending": false,
        "display_name_with_invitation_email_address": "CharactR",
        "email_hash": "91320ea64bd45994d289473f1f5319f0",
        "username": "CharactR",
        "display_name": "CharactR",
        "attached_participatable_portrait_url": "https://s3.amazonaws.com/challonge_app/users/images/003/124/063/xlarge/MonkaSoS.png",
        "can_check_in": false,
        "checked_in": true,
        "reactivatable": false,
        "check_in_open": false,
        "group_player_ids": [],
        "has_irrelevant_seed": false,
        "ordinal_seed": "14th",
        "roster_complete": null,
        "roster_size": null
    },
    {
        "id": 150058474,
        "tournament_id": 9980037,
        "name": "Fletch_sc2",
        "seed": 15,
        "active": true,
        "created_at": "2021/07/05",
        "updated_at": "2021/07/05",
        "invite_email": null,
        "final_rank": 17,
        "misc": null,
        "icon": null,
        "on_waiting_list": false,
        "invitation_id": null,
        "group_id": null,
        "checked_in_at": "2021/07/09",
        "ranked_member_id": null,
        "custom_field_response": {
            "16432": "Yes",
            "16433": "Yes"
        },
        "clinch": null,
        "integration_uids": null,
        "challonge_username": "Fletch_sc2",
        "challonge_user_id": 3349249,
        "challonge_email_address_verified": true,
        "removable": false,
        "participatable_or_invitation_attached": true,
        "confirm_remove": true,
        "invitation_pending": false,
        "display_name_with_invitation_email_address": "Fletch_sc2",
        "email_hash": "a15c08a10065ad57b4204f88b1cc26e6",
        "username": "Fletch_sc2",
        "display_name": "Fletch_sc2",
        "attached_participatable_portrait_url": "https://secure.gravatar.com/avatar/a15c08a10065ad57b4204f88b1cc26e6?r=r&s=96&d=https://s3.amazonaws.com/challonge_app/misc/challonge_fireball_gray.png",
        "can_check_in": false,
        "checked_in": true,
        "reactivatable": false,
        "check_in_open": false,
        "group_player_ids": [],
        "has_irrelevant_seed": false,
        "ordinal_seed": "15th",
        "roster_complete": null,
        "roster_size": null
    },
    {
        "id": 150367459,
        "tournament_id": 9980037,
        "name": "cheoklate",
        "seed": 16,
        "active": true,
        "created_at": "2021/07/09",
        "updated_at": "2021/07/09",
        "invite_email": null,
        "final_rank": 9,
        "misc": null,
        "icon": null,
        "on_waiting_list": false,
        "invitation_id": null,
        "group_id": null,
        "checked_in_at": "2021/07/09",
        "ranked_member_id": null,
        "custom_field_response": {
            "16432": "Yes",
            "16433": "No, but I'll do it now!",
            "16434": "true"
        },
        "clinch": null,
        "integration_uids": null,
        "challonge_username": "cheoklate",
        "challonge_user_id": 3532995,
        "challonge_email_address_verified": true,
        "removable": false,
        "participatable_or_invitation_attached": true,
        "confirm_remove": true,
        "invitation_pending": false,
        "display_name_with_invitation_email_address": "cheoklate",
        "email_hash": "b75381029e428148627630ed77a53db0",
        "username": "cheoklate",
        "display_name": "cheoklate",
        "attached_participatable_portrait_url": "https://secure.gravatar.com/avatar/b75381029e428148627630ed77a53db0?r=r&s=96&d=https://s3.amazonaws.com/challonge_app/misc/challonge_fireball_gray.png",
        "can_check_in": false,
        "checked_in": true,
        "reactivatable": false,
        "check_in_open": false,
        "group_player_ids": [],
        "has_irrelevant_seed": false,
        "ordinal_seed": "16th",
        "roster_complete": null,
        "roster_size": null
    },
    {
        "id": 150367622,
        "tournament_id": 9980037,
        "name": "IIEleven11",
        "seed": 17,
        "active": true,
        "created_at": "2021/07/09",
        "updated_at": "2021/07/09",
        "invite_email": null,
        "final_rank": 17,
        "misc": null,
        "icon": null,
        "on_waiting_list": false,
        "invitation_id": null,
        "group_id": null,
        "checked_in_at": "2021/07/09",
        "ranked_member_id": null,
        "custom_field_response": {
            "16432": "Yes",
            "16433": "Yes"
        },
        "clinch": null,
        "integration_uids": null,
        "challonge_username": "IIEleven11",
        "challonge_user_id": 3551971,
        "challonge_email_address_verified": true,
        "removable": false,
        "participatable_or_invitation_attached": true,
        "confirm_remove": true,
        "invitation_pending": false,
        "display_name_with_invitation_email_address": "IIEleven11",
        "email_hash": "175be3381fafa84e646a5dbe97b27be5",
        "username": "IIEleven11",
        "display_name": "IIEleven11",
        "attached_participatable_portrait_url": "https://s3.amazonaws.com/challonge_app/users/images/003/551/971/xlarge/elevenlogocrow_copys_copy_2_copy_2.png",
        "can_check_in": false,
        "checked_in": true,
        "reactivatable": false,
        "check_in_open": false,
        "group_player_ids": [],
        "has_irrelevant_seed": false,
        "ordinal_seed": "17th",
        "roster_complete": null,
        "roster_size": null
    },
    {
        "id": 149748971,
        "tournament_id": 9980037,
        "name": "Vespasian1884",
        "seed": 18,
        "active": true,
        "created_at": "2021/06/30",
        "updated_at": "2021/06/30",
        "invite_email": null,
        "final_rank": 9,
        "misc": null,
        "icon": null,
        "on_waiting_list": false,
        "invitation_id": null,
        "group_id": null,
        "checked_in_at": "2021/07/09",
        "ranked_member_id": null,
        "custom_field_response": {
            "16432": "Yes",
            "16433": "No, but I'll do it now!"
        },
        "clinch": null,
        "integration_uids": null,
        "challonge_username": "Vespasian1884",
        "challonge_user_id": 554401,
        "challonge_email_address_verified": true,
        "removable": false,
        "participatable_or_invitation_attached": true,
        "confirm_remove": true,
        "invitation_pending": false,
        "display_name_with_invitation_email_address": "Vespasian1884",
        "email_hash": "30695fde957918960adb781fe88dbc37",
        "username": "Vespasian1884",
        "display_name": "Vespasian1884",
        "attached_participatable_portrait_url": "https://s3.amazonaws.com/challonge_app/users/images/000/554/401/xlarge/punisher_large.png",
        "can_check_in": false,
        "checked_in": true,
        "reactivatable": false,
        "check_in_open": false,
        "group_player_ids": [],
        "has_irrelevant_seed": false,
        "ordinal_seed": "18th",
        "roster_complete": null,
        "roster_size": null
    },
    {
        "id": 150310406,
        "tournament_id": 9980037,
        "name": "FireKlaw",
        "seed": 19,
        "active": true,
        "created_at": "2021/07/08",
        "updated_at": "2021/07/08",
        "invite_email": null,
        "final_rank": 2,
        "misc": null,
        "icon": null,
        "on_waiting_list": false,
        "invitation_id": null,
        "group_id": null,
        "checked_in_at": "2021/07/09",
        "ranked_member_id": null,
        "custom_field_response": {
            "16432": "Yes",
            "16433": "Yes"
        },
        "clinch": null,
        "integration_uids": null,
        "challonge_username": "FireKlaw",
        "challonge_user_id": 2069393,
        "challonge_email_address_verified": true,
        "removable": false,
        "participatable_or_invitation_attached": true,
        "confirm_remove": true,
        "invitation_pending": false,
        "display_name_with_invitation_email_address": "FireKlaw",
        "email_hash": "c66685e0ddf32bb212568055edc171c9",
        "username": "FireKlaw",
        "display_name": "FireKlaw",
        "attached_participatable_portrait_url": "https://s3.amazonaws.com/challonge_app/users/images/002/069/393/xlarge/il_1140xN.2303131726_lpxc.png",
        "can_check_in": false,
        "checked_in": true,
        "reactivatable": false,
        "check_in_open": false,
        "group_player_ids": [],
        "has_irrelevant_seed": false,
        "ordinal_seed": "19th",
        "roster_complete": null,
        "roster_size": null
    },
    {
        "id": 150350922,
        "tournament_id": 9980037,
        "name": "RARKA",
        "seed": 20,
        "active": false,
        "created_at": "2021/07/09",
        "updated_at": "2021/07/09",
        "invite_email": null,
        "final_rank": null,
        "misc": null,
        "icon": null,
        "on_waiting_list": false,
        "invitation_id": null,
        "group_id": null,
        "checked_in_at": null,
        "ranked_member_id": null,
        "custom_field_response": {
            "16432": "Yes",
            "16433": "Yes",
            "16434": "true"
        },
        "clinch": null,
        "integration_uids": null,
        "challonge_username": "RARKA",
        "challonge_user_id": 4674154,
        "challonge_email_address_verified": true,
        "removable": false,
        "participatable_or_invitation_attached": true,
        "confirm_remove": true,
        "invitation_pending": false,
        "display_name_with_invitation_email_address": "RARKA",
        "email_hash": "d36442f0a101d5524ebd9493e8adfa88",
        "username": "RARKA",
        "display_name": "RARKA",
        "attached_participatable_portrait_url": "https://secure.gravatar.com/avatar/d36442f0a101d5524ebd9493e8adfa88?r=r&s=96&d=https://s3.amazonaws.com/challonge_app/misc/challonge_fireball_gray.png",
        "can_check_in": false,
        "checked_in": false,
        "reactivatable": false,
        "check_in_open": false,
        "group_player_ids": [],
        "has_irrelevant_seed": true,
        "ordinal_seed": "20th",
        "roster_complete": null,
        "roster_size": null
    },
    {
        "id": 150057740,
        "tournament_id": 9980037,
        "name": "RAMEN14",
        "seed": 21,
        "active": false,
        "created_at": "2021/07/05",
        "updated_at": "2021/07/09",
        "invite_email": null,
        "final_rank": null,
        "misc": null,
        "icon": null,
        "on_waiting_list": false,
        "invitation_id": null,
        "group_id": null,
        "checked_in_at": null,
        "ranked_member_id": null,
        "custom_field_response": {
            "16432": "Yes",
            "16433": "No, but I'll do it now!"
        },
        "clinch": null,
        "integration_uids": null,
        "challonge_username": "RAMEN14",
        "challonge_user_id": 3536627,
        "challonge_email_address_verified": true,
        "removable": false,
        "participatable_or_invitation_attached": true,
        "confirm_remove": true,
        "invitation_pending": false,
        "display_name_with_invitation_email_address": "RAMEN14",
        "email_hash": "ff09f617868d02714b464e82faf38cd5",
        "username": "RAMEN14",
        "display_name": "RAMEN14",
        "attached_participatable_portrait_url": "https://s3.amazonaws.com/challonge_app/users/images/003/536/627/xlarge/Captura_de_pantalla_2023-12-07_180045.png",
        "can_check_in": false,
        "checked_in": false,
        "reactivatable": false,
        "check_in_open": false,
        "group_player_ids": [],
        "has_irrelevant_seed": true,
        "ordinal_seed": "21st",
        "roster_complete": null,
        "roster_size": null
    },
    {
        "id": 150041688,
        "tournament_id": 9980037,
        "name": "dlsmizel",
        "seed": 22,
        "active": false,
        "created_at": "2021/07/04",
        "updated_at": "2021/07/04",
        "invite_email": null,
        "final_rank": null,
        "misc": null,
        "icon": null,
        "on_waiting_list": false,
        "invitation_id": null,
        "group_id": null,
        "checked_in_at": null,
        "ranked_member_id": null,
        "custom_field_response": {
            "16432": "Yes",
            "16433": "Yes"
        },
        "clinch": null,
        "integration_uids": null,
        "challonge_username": "dlsmizel",
        "challonge_user_id": 3851921,
        "challonge_email_address_verified": true,
        "removable": false,
        "participatable_or_invitation_attached": true,
        "confirm_remove": true,
        "invitation_pending": false,
        "display_name_with_invitation_email_address": "dlsmizel",
        "email_hash": "87df9477ca8454c67842ed308ea293c6",
        "username": "dlsmizel",
        "display_name": "dlsmizel",
        "attached_participatable_portrait_url": "https://s3.amazonaws.com/challonge_app/users/images/003/851/921/xlarge/94143897_10164487027655725_7601711523982999552_n.png",
        "can_check_in": false,
        "checked_in": false,
        "reactivatable": false,
        "check_in_open": false,
        "group_player_ids": [],
        "has_irrelevant_seed": true,
        "ordinal_seed": "22nd",
        "roster_complete": null,
        "roster_size": null
    },
    {
        "id": 150224155,
        "tournament_id": 9980037,
        "name": "Eido01",
        "seed": 23,
        "active": false,
        "created_at": "2021/07/07",
        "updated_at": "2021/07/07",
        "invite_email": null,
        "final_rank": null,
        "misc": null,
        "icon": null,
        "on_waiting_list": false,
        "invitation_id": null,
        "group_id": null,
        "checked_in_at": null,
        "ranked_member_id": null,
        "custom_field_response": {
            "16432": "Yes",
            "16433": "No, but I'll do it now!",
            "16434": "true"
        },
        "clinch": null,
        "integration_uids": null,
        "challonge_username": "Eido01",
        "challonge_user_id": 3985800,
        "challonge_email_address_verified": true,
        "removable": false,
        "participatable_or_invitation_attached": true,
        "confirm_remove": true,
        "invitation_pending": false,
        "display_name_with_invitation_email_address": "Eido01",
        "email_hash": "b0427574f4d11d64e5977a2168da52a8",
        "username": "Eido01",
        "display_name": "Eido01",
        "attached_participatable_portrait_url": "https://secure.gravatar.com/avatar/b0427574f4d11d64e5977a2168da52a8?r=r&s=96&d=https://s3.amazonaws.com/challonge_app/misc/challonge_fireball_gray.png",
        "can_check_in": false,
        "checked_in": false,
        "reactivatable": false,
        "check_in_open": false,
        "group_player_ids": [],
        "has_irrelevant_seed": true,
        "ordinal_seed": "23rd",
        "roster_complete": null,
        "roster_size": null
    },
    {
        "id": 149632203,
        "tournament_id": 9980037,
        "name": "ADEC_SlayersMvP",
        "seed": 24,
        "active": false,
        "created_at": "2021/06/29",
        "updated_at": "2021/06/29",
        "invite_email": null,
        "final_rank": null,
        "misc": null,
        "icon": null,
        "on_waiting_list": false,
        "invitation_id": null,
        "group_id": null,
        "checked_in_at": null,
        "ranked_member_id": null,
        "custom_field_response": {
            "16432": "Yes",
            "16433": "Yes",
            "16434": "true"
        },
        "clinch": null,
        "integration_uids": null,
        "challonge_username": "ADEC_SlayersMvP",
        "challonge_user_id": 4499077,
        "challonge_email_address_verified": true,
        "removable": false,
        "participatable_or_invitation_attached": true,
        "confirm_remove": true,
        "invitation_pending": false,
        "display_name_with_invitation_email_address": "ADEC_SlayersMvP",
        "email_hash": "09370f6e7305d728ab9414ab9e36a393",
        "username": "ADEC_SlayersMvP",
        "display_name": "ADEC_SlayersMvP",
        "attached_participatable_portrait_url": "https://s3.amazonaws.com/challonge_app/users/images/004/499/077/xlarge/Pron%C3%B3sticos-MVP-NBA-Marathonbet-696x520.png",
        "can_check_in": false,
        "checked_in": false,
        "reactivatable": false,
        "check_in_open": false,
        "group_player_ids": [],
        "has_irrelevant_seed": true,
        "ordinal_seed": "24th",
        "roster_complete": null,
        "roster_size": null
    },
    {
        "id": 150232769,
        "tournament_id": 9980037,
        "name": "ShieldedDusk",
        "seed": 25,
        "active": false,
        "created_at": "2021/07/07",
        "updated_at": "2021/07/07",
        "invite_email": null,
        "final_rank": null,
        "misc": null,
        "icon": null,
        "on_waiting_list": false,
        "invitation_id": null,
        "group_id": null,
        "checked_in_at": null,
        "ranked_member_id": null,
        "custom_field_response": {
            "16432": "Yes",
            "16433": "Yes",
            "16434": "true"
        },
        "clinch": null,
        "integration_uids": null,
        "challonge_username": "ShieldedDusk",
        "challonge_user_id": 4271545,
        "challonge_email_address_verified": true,
        "removable": false,
        "participatable_or_invitation_attached": true,
        "confirm_remove": true,
        "invitation_pending": false,
        "display_name_with_invitation_email_address": "ShieldedDusk",
        "email_hash": "790b60ef5ef18c8ed32aac1cd1725850",
        "username": "ShieldedDusk",
        "display_name": "ShieldedDusk",
        "attached_participatable_portrait_url": "https://secure.gravatar.com/avatar/790b60ef5ef18c8ed32aac1cd1725850?r=r&s=96&d=https://s3.amazonaws.com/challonge_app/misc/challonge_fireball_gray.png",
        "can_check_in": false,
        "checked_in": false,
        "reactivatable": false,
        "check_in_open": false,
        "group_player_ids": [],
        "has_irrelevant_seed": true,
        "ordinal_seed": "25th",
        "roster_complete": null,
        "roster_size": null
    },
    {
        "id": 149684969,
        "tournament_id": 9980037,
        "name": "PancakeEmpire",
        "seed": 26,
        "active": false,
        "created_at": "2021/06/30",
        "updated_at": "2021/06/30",
        "invite_email": null,
        "final_rank": null,
        "misc": null,
        "icon": null,
        "on_waiting_list": false,
        "invitation_id": null,
        "group_id": null,
        "checked_in_at": null,
        "ranked_member_id": null,
        "custom_field_response": {
            "16432": "Yes",
            "16433": "No, but I'll do it now!"
        },
        "clinch": null,
        "integration_uids": null,
        "challonge_username": "PatchesSC2",
        "challonge_user_id": 4931331,
        "challonge_email_address_verified": true,
        "removable": false,
        "participatable_or_invitation_attached": true,
        "confirm_remove": true,
        "invitation_pending": false,
        "display_name_with_invitation_email_address": "PancakeEmpire",
        "email_hash": "326c64bc57ff70ddbc93e6f091ab07dd",
        "username": "PatchesSC2",
        "display_name": "PancakeEmpire",
        "attached_participatable_portrait_url": "https://s3.amazonaws.com/challonge_app/users/images/004/931/331/xlarge/ThisIsJimmy.png",
        "can_check_in": false,
        "checked_in": false,
        "reactivatable": false,
        "check_in_open": false,
        "group_player_ids": [],
        "has_irrelevant_seed": true,
        "ordinal_seed": "26th",
        "roster_complete": null,
        "roster_size": null
    },
    {
        "id": 150316531,
        "tournament_id": 9980037,
        "name": "Sc2Pete",
        "seed": 27,
        "active": false,
        "created_at": "2021/07/09",
        "updated_at": "2021/07/09",
        "invite_email": null,
        "final_rank": null,
        "misc": null,
        "icon": null,
        "on_waiting_list": false,
        "invitation_id": null,
        "group_id": null,
        "checked_in_at": null,
        "ranked_member_id": null,
        "custom_field_response": {
            "16432": "Yes",
            "16433": "Yes"
        },
        "clinch": null,
        "integration_uids": null,
        "challonge_username": "Sc2Pete",
        "challonge_user_id": 4665747,
        "challonge_email_address_verified": true,
        "removable": false,
        "participatable_or_invitation_attached": true,
        "confirm_remove": true,
        "invitation_pending": false,
        "display_name_with_invitation_email_address": "Sc2Pete",
        "email_hash": "683ef8593ab06981b1937e486b3c7e28",
        "username": "Sc2Pete",
        "display_name": "Sc2Pete",
        "attached_participatable_portrait_url": "https://secure.gravatar.com/avatar/683ef8593ab06981b1937e486b3c7e28?r=r&s=96&d=https://s3.amazonaws.com/challonge_app/misc/challonge_fireball_gray.png",
        "can_check_in": false,
        "checked_in": false,
        "reactivatable": false,
        "check_in_open": false,
        "group_player_ids": [],
        "has_irrelevant_seed": true,
        "ordinal_seed": "27th",
        "roster_complete": null,
        "roster_size": null
    }
]